brawlstarswrapper/__init__.py
brawlstarswrapper/models.py
brawlstarswrapper-0.0.1.dist-info/LICENSE.txt
brawlstarswrapper-0.0.1.dist-info/METADATA
brawlstarswrapper-0.0.1.dist-info/WHEEL
brawlstarswrapper-0.0.1.dist-info/top_level.txt
brawlstarswrapper-0.0.1.dist-info/RECORD
