Metadata-Version: 2.1
Name: brawlstarswrapper
Version: 0.0.1
Summary: A wrapper for a brawl stars api
Home-page: UNKNOWN
Author: Muhammad Shafeeq
Author-email: <contactme@aspireyoung.me>
License: UNKNOWN
Keywords: python,Brawl Stars API,Requests
Platform: UNKNOWN
Classifier: Development Status :: 1 - Planning
Classifier: Intended Audience :: Developers
Classifier: Programming Language :: Python :: 3
Classifier: Operating System :: Unix
Classifier: Operating System :: MacOS :: MacOS X
Classifier: Operating System :: Microsoft :: Windows
Requires-Dist: requests
